spark_simplicity/__init__.py
spark_simplicity/exceptions.py
spark_simplicity/joins.py
spark_simplicity/logger.py
spark_simplicity/notification_service.py
spark_simplicity/session.py
spark_simplicity/utils.py
spark_simplicity/connections/__init__.py
spark_simplicity/connections/database_connection.py
spark_simplicity/connections/email_connection.py
spark_simplicity/connections/rest_api_connection.py
spark_simplicity/connections/sftp_connection.py
spark_simplicity/io/__init__.py
spark_simplicity/io/readers/__init__.py
spark_simplicity/io/readers/base_reader.py
spark_simplicity/io/readers/csv_reader.py
spark_simplicity/io/readers/excel_reader.py
spark_simplicity/io/readers/json_reader.py
spark_simplicity/io/readers/parquet_reader.py
spark_simplicity/io/readers/text_reader.py
spark_simplicity/io/utils/__init__.py
spark_simplicity/io/utils/file_utils.py
spark_simplicity/io/utils/format_utils.py
spark_simplicity/io/validation/__init__.py
spark_simplicity/io/validation/mount_validator.py
spark_simplicity/io/validation/path_utils.py
spark_simplicity/io/writers/__init__.py
spark_simplicity/io/writers/base_writer.py
spark_simplicity/io/writers/csv_writer.py
spark_simplicity/io/writers/excel_writer.py
spark_simplicity/io/writers/json_writer.py
spark_simplicity/io/writers/parquet_writer.py
spark_simplicity/io/writers/text_writer.py
spark_simplicity-1.1.0.dist-info/licenses/LICENSE
tests/__init__.py
tests/conftest.py
tests/test_exceptions.py
tests/test_logger.py
tests/test_property_based.py
tests/test_security.py
tests/test_session.py
tests/test_utils.py
tests/connections/__init__.py
tests/connections/conftest.py
tests/connections/test_database_connection.py
tests/connections/test_email_connection.py
tests/connections/test_rest_api_connection.py
tests/connections/test_sftp_connection.py
spark_simplicity-1.1.0.dist-info/METADATA
spark_simplicity-1.1.0.dist-info/WHEEL
spark_simplicity-1.1.0.dist-info/top_level.txt
spark_simplicity-1.1.0.dist-info/RECORD
