Metadata-Version: 2.4
Name: spark-simplicity
Version: 1.1.0
Summary: Simplify Apache Spark operations with an intuitive Python API
Author-email: "F. Barrios" <fabienbarrios@gmail.com>
License-Expression: MIT
Project-URL: Homepage, https://github.com/FabienBarrios/spark-simplicity
Project-URL: Documentation, https://spark-simplicity.readthedocs.io
Project-URL: Repository, https://github.com/FabienBarrios/spark-simplicity.git
Project-URL: Issues, https://github.com/FabienBarrios/spark-simplicity/issues
Keywords: spark,pyspark,big-data,data-engineering,etl
Classifier: Development Status :: 5 - Production/Stable
Classifier: Intended Audience :: Developers
Classifier: Topic :: Software Development :: Libraries :: Python Modules
Classifier: Topic :: Scientific/Engineering :: Information Analysis
Classifier: Programming Language :: Python :: 3
Classifier: Programming Language :: Python :: 3.8
Classifier: Programming Language :: Python :: 3.9
Classifier: Programming Language :: Python :: 3.10
Classifier: Programming Language :: Python :: 3.11
Classifier: Programming Language :: Python :: 3.12
Requires-Python: >=3.8
License-File: LICENSE
Requires-Dist: pyspark>=3.5.0
Requires-Dist: pandas>=2.0.0
Requires-Dist: openpyxl>=3.0.0
Requires-Dist: requests>=2.28.0
Requires-Dist: paramiko>=2.9.0
Requires-Dist: pyarrow>=10.0.0
Requires-Dist: fastparquet>=0.8.3
Provides-Extra: dev
Requires-Dist: pytest>=7.0.0; extra == "dev"
Requires-Dist: pytest-cov>=4.0.0; extra == "dev"
Requires-Dist: pytest-mock>=3.10.0; extra == "dev"
Requires-Dist: pytest-xdist>=3.0.0; extra == "dev"
Requires-Dist: pytest-benchmark>=4.0.0; extra == "dev"
Requires-Dist: pytest-timeout>=2.1.0; extra == "dev"
Requires-Dist: coverage[toml]>=7.0.0; extra == "dev"
Requires-Dist: black>=22.0.0; extra == "dev"
Requires-Dist: isort>=5.10.0; extra == "dev"
Requires-Dist: flake8>=4.0.0; extra == "dev"
Requires-Dist: flake8-docstrings>=1.7.0; extra == "dev"
Requires-Dist: flake8-bugbear>=23.0.0; extra == "dev"
Requires-Dist: mypy>=0.991; extra == "dev"
Requires-Dist: bandit>=1.7.0; extra == "dev"
Requires-Dist: hypothesis>=6.0.0; extra == "dev"
Requires-Dist: pre-commit>=3.0.0; extra == "dev"
Provides-Extra: docs
Requires-Dist: sphinx>=4.0.0; extra == "docs"
Requires-Dist: sphinx-rtd-theme>=1.0.0; extra == "docs"
Provides-Extra: database
Requires-Dist: pyodbc>=4.0.0; extra == "database"
Requires-Dist: pymssql>=2.2.0; extra == "database"
Dynamic: license-file
